<?xml version="1.0" encoding="utf-8"?>
<TextureAtlas imagePath="neetblue.png">
	<!-- Created with Adobe Animate version 22.0.0.93 -->
	<!-- http://www.adobe.com/products/animate.html -->
	<SubTexture name="s down0000" x="2" y="2" width="323" height="476"/>
	<SubTexture name="s down0001" x="2" y="2" width="323" height="476"/>
	<SubTexture name="s down0002" x="330" y="2" width="323" height="476"/>
	<SubTexture name="s down0003" x="330" y="2" width="323" height="476"/>
	<SubTexture name="s down0004" x="330" y="2" width="323" height="476"/>
	<SubTexture name="s down0005" x="330" y="2" width="323" height="476"/>
	<SubTexture name="s down0006" x="330" y="2" width="323" height="476"/>
	<SubTexture name="s down0007" x="330" y="2" width="323" height="476"/>
	<SubTexture name="s down0008" x="330" y="2" width="323" height="476"/>
	<SubTexture name="s down0009" x="330" y="2" width="323" height="476"/>
	<SubTexture name="s down0010" x="330" y="2" width="323" height="476"/>
	<SubTexture name="s down0011" x="330" y="2" width="323" height="476"/>
	<SubTexture name="s down0012" x="330" y="2" width="323" height="476"/>
	<SubTexture name="s down0013" x="330" y="2" width="323" height="476"/>
	<SubTexture name="s id0000" x="658" y="2" width="304" height="528"/>
	<SubTexture name="s id0001" x="658" y="2" width="304" height="528"/>
	<SubTexture name="s id0002" x="967" y="2" width="304" height="528"/>
	<SubTexture name="s id0003" x="967" y="2" width="304" height="528"/>
	<SubTexture name="s id0004" x="1276" y="2" width="304" height="528"/>
	<SubTexture name="s id0005" x="1276" y="2" width="304" height="528"/>
	<SubTexture name="s id0006" x="1585" y="2" width="304" height="528"/>
	<SubTexture name="s id0007" x="1585" y="2" width="304" height="528"/>
	<SubTexture name="s id0008" x="2" y="535" width="304" height="528"/>
	<SubTexture name="s id0009" x="2" y="535" width="304" height="528"/>
	<SubTexture name="s id0010" x="311" y="535" width="304" height="528"/>
	<SubTexture name="s id0011" x="311" y="535" width="304" height="528"/>
	<SubTexture name="s id0012" x="2" y="535" width="304" height="528"/>
	<SubTexture name="s id0013" x="2" y="535" width="304" height="528"/>
	<SubTexture name="s left0000" x="620" y="535" width="303" height="535"/>
	<SubTexture name="s left0001" x="620" y="535" width="303" height="535"/>
	<SubTexture name="s left0002" x="928" y="535" width="303" height="535"/>
	<SubTexture name="s left0003" x="928" y="535" width="303" height="535"/>
	<SubTexture name="s left0004" x="928" y="535" width="303" height="535"/>
	<SubTexture name="s left0005" x="928" y="535" width="303" height="535"/>
	<SubTexture name="s left0006" x="928" y="535" width="303" height="535"/>
	<SubTexture name="s left0007" x="928" y="535" width="303" height="535"/>
	<SubTexture name="s left0008" x="928" y="535" width="303" height="535"/>
	<SubTexture name="s left0009" x="928" y="535" width="303" height="535"/>
	<SubTexture name="s left0010" x="928" y="535" width="303" height="535"/>
	<SubTexture name="s left0011" x="928" y="535" width="303" height="535"/>
	<SubTexture name="s left0012" x="928" y="535" width="303" height="535"/>
	<SubTexture name="s left0013" x="928" y="535" width="303" height="535"/>
	<SubTexture name="s right0000" x="1236" y="535" width="278" height="522"/>
	<SubTexture name="s right0001" x="1236" y="535" width="278" height="522"/>
	<SubTexture name="s right0002" x="1519" y="535" width="278" height="522"/>
	<SubTexture name="s right0003" x="1519" y="535" width="278" height="522"/>
	<SubTexture name="s right0004" x="1519" y="535" width="278" height="522"/>
	<SubTexture name="s right0005" x="1519" y="535" width="278" height="522"/>
	<SubTexture name="s right0006" x="1519" y="535" width="278" height="522"/>
	<SubTexture name="s right0007" x="1519" y="535" width="278" height="522"/>
	<SubTexture name="s right0008" x="1519" y="535" width="278" height="522"/>
	<SubTexture name="s right0009" x="1519" y="535" width="278" height="522"/>
	<SubTexture name="s right0010" x="1519" y="535" width="278" height="522"/>
	<SubTexture name="s right0011" x="1519" y="535" width="278" height="522"/>
	<SubTexture name="s right0012" x="1519" y="535" width="278" height="522"/>
	<SubTexture name="s right0013" x="1519" y="535" width="278" height="522"/>
	<SubTexture name="s up0000" x="2" y="1075" width="288" height="571"/>
	<SubTexture name="s up0001" x="2" y="1075" width="288" height="571"/>
	<SubTexture name="s up0002" x="295" y="1075" width="288" height="571"/>
	<SubTexture name="s up0003" x="295" y="1075" width="288" height="571"/>
	<SubTexture name="s up0004" x="295" y="1075" width="288" height="571"/>
	<SubTexture name="s up0005" x="295" y="1075" width="288" height="571"/>
	<SubTexture name="s up0006" x="295" y="1075" width="288" height="571"/>
	<SubTexture name="s up0007" x="295" y="1075" width="288" height="571"/>
	<SubTexture name="s up0008" x="295" y="1075" width="288" height="571"/>
	<SubTexture name="s up0009" x="295" y="1075" width="288" height="571"/>
	<SubTexture name="s up0010" x="295" y="1075" width="288" height="571"/>
	<SubTexture name="s up0011" x="295" y="1075" width="288" height="571"/>
	<SubTexture name="s up0012" x="295" y="1075" width="288" height="571"/>
	<SubTexture name="s up0013" x="295" y="1075" width="288" height="571"/>
</TextureAtlas>
